{
  "_cached_at": "2026-07-01T03:58:50.700846",
  "payload": [
    {
      "agent": "ASUNAPREVIR",
      "agent_id": "rxcui:1652103",
      "interaction_type": "unknown",
      "direction": "unclear",
      "source": "DGIdb",
      "source_url": "https://dgidb.org/genes/IFNL3",
      "evidence_tier": "mechanistic",
      "potency": {
        "value": null,
        "unit": null,
        "measure": null
      },
      "pubmed_ids": [
        "31144350"
      ],
      "raw": {
        "score": 1.392101294903614
      }
    },
    {
      "agent": "VOXILAPREVIR",
      "agent_id": "rxcui:1939323",
      "interaction_type": "unknown",
      "direction": "unclear",
      "source": "DGIdb",
      "source_url": "https://dgidb.org/genes/IFNL3",
      "evidence_tier": "mechanistic",
      "potency": {
        "value": null,
        "unit": null,
        "measure": null
      },
      "pubmed_ids": [
        "29107709"
      ],
      "raw": {
        "score": 2.088151942355421
      }
    },
    {
      "agent": "PARITAPREVIR",
      "agent_id": "rxcui:1597373",
      "interaction_type": "unknown",
      "direction": "unclear",
      "source": "DGIdb",
      "source_url": "https://dgidb.org/genes/IFNL3",
      "evidence_tier": "mechanistic",
      "potency": {
        "value": null,
        "unit": null,
        "measure": null
      },
      "pubmed_ids": [],
      "raw": {
        "score": 1.04407597117771
      }
    },
    {
      "agent": "SIMEPREVIR",
      "agent_id": "rxcui:1482790",
      "interaction_type": "unknown",
      "direction": "unclear",
      "source": "DGIdb",
      "source_url": "https://dgidb.org/genes/IFNL3",
      "evidence_tier": "mechanistic",
      "potency": {
        "value": null,
        "unit": null,
        "measure": null
      },
      "pubmed_ids": [
        "28261382",
        "26264253",
        "24602923",
        "28072888",
        "28506030",
        "24907224",
        "27027531"
      ],
      "raw": {
        "score": 9.396683740599396
      }
    },
    {
      "agent": "OMBITASVIR",
      "agent_id": "rxcui:1597371",
      "interaction_type": "unknown",
      "direction": "unclear",
      "source": "DGIdb",
      "source_url": "https://dgidb.org/genes/IFNL3",
      "evidence_tier": "mechanistic",
      "potency": {
        "value": null,
        "unit": null,
        "measure": null
      },
      "pubmed_ids": [],
      "raw": {
        "score": 2.088151942355421
      }
    },
    {
      "agent": "INTERFERON ALFA-N1",
      "agent_id": "rxcui:202912",
      "interaction_type": "unknown",
      "direction": "unclear",
      "source": "DGIdb",
      "source_url": "https://dgidb.org/genes/IFNL3",
      "evidence_tier": "mechanistic",
      "potency": {
        "value": null,
        "unit": null,
        "measure": null
      },
      "pubmed_ids": [
        "21466653"
      ],
      "raw": {
        "score": 1.04407597117771
      }
    },
    {
      "agent": "ELBASVIR/GRAZOPREVIR",
      "agent_id": "wikidata:Q22673321",
      "interaction_type": "unknown",
      "direction": "unclear",
      "source": "DGIdb",
      "source_url": "https://dgidb.org/genes/IFNL3",
      "evidence_tier": "mechanistic",
      "potency": {
        "value": null,
        "unit": null,
        "measure": null
      },
      "pubmed_ids": [
        "31846553"
      ],
      "raw": {
        "score": 2.088151942355421
      }
    },
    {
      "agent": "SOFOSBUVIR",
      "agent_id": "rxcui:1484911",
      "interaction_type": "unknown",
      "direction": "unclear",
      "source": "DGIdb",
      "source_url": "https://dgidb.org/genes/IFNL3",
      "evidence_tier": "mechanistic",
      "potency": {
        "value": null,
        "unit": null,
        "measure": null
      },
      "pubmed_ids": [
        "29534310",
        "29107709",
        "29504692",
        "27357737",
        "34843922",
        "28100007",
        "25734178",
        "30431653"
      ],
      "raw": {
        "score": 10.4407597117771
      }
    },
    {
      "agent": "LEDIPASVIR",
      "agent_id": "rxcui:1591922",
      "interaction_type": "unknown",
      "direction": "unclear",
      "source": "DGIdb",
      "source_url": "https://dgidb.org/genes/IFNL3",
      "evidence_tier": "mechanistic",
      "potency": {
        "value": null,
        "unit": null,
        "measure": null
      },
      "pubmed_ids": [
        "29504692",
        "27357737",
        "28100007",
        "25734178"
      ],
      "raw": {
        "score": 6.264455827066264
      }
    },
    {
      "agent": "DELEOBUVIR",
      "agent_id": "ncit:C166826",
      "interaction_type": "unknown",
      "direction": "unclear",
      "source": "DGIdb",
      "source_url": "https://dgidb.org/genes/IFNL3",
      "evidence_tier": "mechanistic",
      "potency": {
        "value": null,
        "unit": null,
        "measure": null
      },
      "pubmed_ids": [
        "23944300"
      ],
      "raw": {
        "score": 2.088151942355421
      }
    },
    {
      "agent": "PEGINTERFERON ALFA-2B",
      "agent_id": "rxcui:253453",
      "interaction_type": "unknown",
      "direction": "unclear",
      "source": "DGIdb",
      "source_url": "https://dgidb.org/genes/IFNL3",
      "evidence_tier": "mechanistic",
      "potency": {
        "value": null,
        "unit": null,
        "measure": null
      },
      "pubmed_ids": [],
      "raw": {
        "score": 0.06525474819860692
      }
    },
    {
      "agent": "DASABUVIR",
      "agent_id": "rxcui:1597381",
      "interaction_type": "unknown",
      "direction": "unclear",
      "source": "DGIdb",
      "source_url": "https://dgidb.org/genes/IFNL3",
      "evidence_tier": "mechanistic",
      "potency": {
        "value": null,
        "unit": null,
        "measure": null
      },
      "pubmed_ids": [],
      "raw": {
        "score": 4.176303884710843
      }
    },
    {
      "agent": "DACLATASVIR",
      "agent_id": "rxcui:1606218",
      "interaction_type": "unknown",
      "direction": "unclear",
      "source": "DGIdb",
      "source_url": "https://dgidb.org/genes/IFNL3",
      "evidence_tier": "mechanistic",
      "potency": {
        "value": null,
        "unit": null,
        "measure": null
      },
      "pubmed_ids": [
        "31144350",
        "34843922",
        "25080450",
        "30431653"
      ],
      "raw": {
        "score": 3.132227913533132
      }
    },
    {
      "agent": "ELBASVIR",
      "agent_id": "rxcui:1734628",
      "interaction_type": "unknown",
      "direction": "unclear",
      "source": "DGIdb",
      "source_url": "https://dgidb.org/genes/IFNL3",
      "evidence_tier": "mechanistic",
      "potency": {
        "value": null,
        "unit": null,
        "measure": null
      },
      "pubmed_ids": [],
      "raw": {
        "score": 2.088151942355421
      }
    },
    {
      "agent": "PEGINTERFERON ALFA-2A",
      "agent_id": "rxcui:120608",
      "interaction_type": "unknown",
      "direction": "unclear",
      "source": "DGIdb",
      "source_url": "https://dgidb.org/genes/IFNL3",
      "evidence_tier": "mechanistic",
      "potency": {
        "value": null,
        "unit": null,
        "measure": null
      },
      "pubmed_ids": [
        "24768758",
        "24102823"
      ],
      "raw": {
        "score": 0.2160157181746987
      }
    },
    {
      "agent": "RITONAVIR",
      "agent_id": "rxcui:85762",
      "interaction_type": "unknown",
      "direction": "unclear",
      "source": "DGIdb",
      "source_url": "https://dgidb.org/genes/IFNL3",
      "evidence_tier": "mechanistic",
      "potency": {
        "value": null,
        "unit": null,
        "measure": null
      },
      "pubmed_ids": [],
      "raw": {
        "score": 0.07733896082797857
      }
    },
    {
      "agent": "SOFOSBUVIR / VELPATASVIR / VOXILAPREVIR",
      "agent_id": "wikidata:Q48564241",
      "interaction_type": "unknown",
      "direction": "unclear",
      "source": "DGIdb",
      "source_url": "https://dgidb.org/genes/IFNL3",
      "evidence_tier": "mechanistic",
      "potency": {
        "value": null,
        "unit": null,
        "measure": null
      },
      "pubmed_ids": [],
      "raw": {
        "score": 2.088151942355421
      }
    },
    {
      "agent": "GRAZOPREVIR",
      "agent_id": "rxcui:1734630",
      "interaction_type": "unknown",
      "direction": "unclear",
      "source": "DGIdb",
      "source_url": "https://dgidb.org/genes/IFNL3",
      "evidence_tier": "mechanistic",
      "potency": {
        "value": null,
        "unit": null,
        "measure": null
      },
      "pubmed_ids": [],
      "raw": {
        "score": 1.04407597117771
      }
    },
    {
      "agent": "FALDAPREVIR",
      "agent_id": "ncit:C171746",
      "interaction_type": "unknown",
      "direction": "unclear",
      "source": "DGIdb",
      "source_url": "https://dgidb.org/genes/IFNL3",
      "evidence_tier": "mechanistic",
      "potency": {
        "value": null,
        "unit": null,
        "measure": null
      },
      "pubmed_ids": [
        "23944300"
      ],
      "raw": {
        "score": 1.392101294903614
      }
    },
    {
      "agent": "VELPATASVIR",
      "agent_id": "rxcui:1799206",
      "interaction_type": "unknown",
      "direction": "unclear",
      "source": "DGIdb",
      "source_url": "https://dgidb.org/genes/IFNL3",
      "evidence_tier": "mechanistic",
      "potency": {
        "value": null,
        "unit": null,
        "measure": null
      },
      "pubmed_ids": [
        "29107709"
      ],
      "raw": {
        "score": 3.132227913533132
      }
    },
    {
      "agent": "TELAPREVIR",
      "agent_id": "rxcui:1102261",
      "interaction_type": "unknown",
      "direction": "unclear",
      "source": "DGIdb",
      "source_url": "https://dgidb.org/genes/IFNL3",
      "evidence_tier": "mechanistic",
      "potency": {
        "value": null,
        "unit": null,
        "measure": null
      },
      "pubmed_ids": [],
      "raw": {
        "score": 0.4176303884710842
      }
    },
    {
      "agent": "OMBITASVIR/PARITAPREVIR/RITONAVIR",
      "agent_id": "wikidata:Q19858657",
      "interaction_type": "unknown",
      "direction": "unclear",
      "source": "DGIdb",
      "source_url": "https://dgidb.org/genes/IFNL3",
      "evidence_tier": "mechanistic",
      "potency": {
        "value": null,
        "unit": null,
        "measure": null
      },
      "pubmed_ids": [
        "31144350"
      ],
      "raw": {
        "score": 2.088151942355421
      }
    },
    {
      "agent": "SOFOSBUVIR/VELPATASVIR",
      "agent_id": "wikidata:Q25110523",
      "interaction_type": "unknown",
      "direction": "unclear",
      "source": "DGIdb",
      "source_url": "https://dgidb.org/genes/IFNL3",
      "evidence_tier": "mechanistic",
      "potency": {
        "value": null,
        "unit": null,
        "measure": null
      },
      "pubmed_ids": [],
      "raw": {
        "score": 2.088151942355421
      }
    },
    {
      "agent": "ATORVASTATIN CALCIUM TRIHYDRATE",
      "agent_id": "rxcui:1297766",
      "interaction_type": "unknown",
      "direction": "unclear",
      "source": "DGIdb",
      "source_url": "https://dgidb.org/genes/IFNL3",
      "evidence_tier": "mechanistic",
      "potency": {
        "value": null,
        "unit": null,
        "measure": null
      },
      "pubmed_ids": [
        "123467"
      ],
      "raw": {
        "score": 0.07593279790383352
      }
    },
    {
      "agent": "BOCEPREVIR",
      "agent_id": "rxcui:1102129",
      "interaction_type": "unknown",
      "direction": "unclear",
      "source": "DGIdb",
      "source_url": "https://dgidb.org/genes/IFNL3",
      "evidence_tier": "mechanistic",
      "potency": {
        "value": null,
        "unit": null,
        "measure": null
      },
      "pubmed_ids": [
        "26670100",
        "28469811",
        "22626609",
        "26191484",
        "24096968",
        "25836019",
        "27711230"
      ],
      "raw": {
        "score": 2.684766783028399
      }
    }
  ]
}