{
  "_cached_at": "2026-07-01T05:30:44.318770",
  "payload": [
    {
      "agent": "RECOMBINANT LYMPHOKINE",
      "agent_id": "ncit:C621",
      "interaction_type": "unknown",
      "direction": "unclear",
      "source": "DGIdb",
      "source_url": "https://dgidb.org/genes/HLA-DQA1",
      "evidence_tier": "mechanistic",
      "potency": {
        "value": null,
        "unit": null,
        "measure": null
      },
      "pubmed_ids": [
        "2166625"
      ],
      "raw": {
        "score": 1.491537101682444
      }
    },
    {
      "agent": "INTERFERON BETA-1B",
      "agent_id": "rxcui:72257",
      "interaction_type": "unknown",
      "direction": "unclear",
      "source": "DGIdb",
      "source_url": "https://dgidb.org/genes/HLA-DQA1",
      "evidence_tier": "mechanistic",
      "potency": {
        "value": null,
        "unit": null,
        "measure": null
      },
      "pubmed_ids": [
        "21502966"
      ],
      "raw": {
        "score": 1.04407597117771
      }
    },
    {
      "agent": "FLOXACILLIN",
      "agent_id": "rxcui:4448",
      "interaction_type": "unknown",
      "direction": "unclear",
      "source": "DGIdb",
      "source_url": "https://dgidb.org/genes/HLA-DQA1",
      "evidence_tier": "mechanistic",
      "potency": {
        "value": null,
        "unit": null,
        "measure": null
      },
      "pubmed_ids": [
        "30661239"
      ],
      "raw": {
        "score": 1.160084412419678
      }
    },
    {
      "agent": "INTERFERON BETA-1A",
      "agent_id": "rxcui:75917",
      "interaction_type": "unknown",
      "direction": "unclear",
      "source": "DGIdb",
      "source_url": "https://dgidb.org/genes/HLA-DQA1",
      "evidence_tier": "mechanistic",
      "potency": {
        "value": null,
        "unit": null,
        "measure": null
      },
      "pubmed_ids": [
        "21502966"
      ],
      "raw": {
        "score": 0.6960506474518071
      }
    },
    {
      "agent": "PEGASPARGASE",
      "agent_id": "rxcui:34132",
      "interaction_type": "unknown",
      "direction": "unclear",
      "source": "DGIdb",
      "source_url": "https://dgidb.org/genes/HLA-DQA1",
      "evidence_tier": "mechanistic",
      "potency": {
        "value": null,
        "unit": null,
        "measure": null
      },
      "pubmed_ids": [
        "33768542"
      ],
      "raw": {
        "score": 0.6960506474518071
      }
    },
    {
      "agent": "MEASLES VACCINE",
      "agent_id": "wikidata:Q6804161",
      "interaction_type": "unknown",
      "direction": "unclear",
      "source": "DGIdb",
      "source_url": "https://dgidb.org/genes/HLA-DQA1",
      "evidence_tier": "mechanistic",
      "potency": {
        "value": null,
        "unit": null,
        "measure": null
      },
      "pubmed_ids": [
        "11672906",
        "15121303"
      ],
      "raw": {
        "score": 3.915284891916414
      }
    },
    {
      "agent": "LUMIRACOXIB",
      "agent_id": "ncit:C66041",
      "interaction_type": "unknown",
      "direction": "unclear",
      "source": "DGIdb",
      "source_url": "https://dgidb.org/genes/HLA-DQA1",
      "evidence_tier": "mechanistic",
      "potency": {
        "value": null,
        "unit": null,
        "measure": null
      },
      "pubmed_ids": [
        "20639878"
      ],
      "raw": {
        "score": 1.740126618629517
      }
    },
    {
      "agent": "MERCAPTOPURINE",
      "agent_id": "rxcui:103",
      "interaction_type": "unknown",
      "direction": "unclear",
      "source": "DGIdb",
      "source_url": "https://dgidb.org/genes/HLA-DQA1",
      "evidence_tier": "mechanistic",
      "potency": {
        "value": null,
        "unit": null,
        "measure": null
      },
      "pubmed_ids": [
        "25217962"
      ],
      "raw": {
        "score": 0.2320168824839356
      }
    },
    {
      "agent": "AZATHIOPRINE",
      "agent_id": "rxcui:1256",
      "interaction_type": "unknown",
      "direction": "unclear",
      "source": "DGIdb",
      "source_url": "https://dgidb.org/genes/HLA-DQA1",
      "evidence_tier": "mechanistic",
      "potency": {
        "value": null,
        "unit": null,
        "measure": null
      },
      "pubmed_ids": [
        "25217962"
      ],
      "raw": {
        "score": 0.2747568345204501
      }
    },
    {
      "agent": "LAPATINIB",
      "agent_id": "rxcui:480167",
      "interaction_type": "unknown",
      "direction": "unclear",
      "source": "DGIdb",
      "source_url": "https://dgidb.org/genes/HLA-DQA1",
      "evidence_tier": "mechanistic",
      "potency": {
        "value": null,
        "unit": null,
        "measure": null
      },
      "pubmed_ids": [
        "21245432",
        "24687830"
      ],
      "raw": {
        "score": 0.6735974007598132
      }
    }
  ]
}