{
  "_cached_at": "2026-07-01T05:14:04.560423",
  "payload": [
    {
      "agent": "PROCAINE HYDROCHLORIDE",
      "agent_id": "rxcui:106558",
      "interaction_type": "blocker",
      "direction": "inhibits",
      "source": "DGIdb",
      "source_url": "https://dgidb.org/genes/SCN2A",
      "evidence_tier": "mechanistic",
      "potency": {
        "value": null,
        "unit": null,
        "measure": null
      },
      "pubmed_ids": [],
      "raw": {
        "score": 0.0828631723156913
      }
    },
    {
      "agent": "PROPOFOL",
      "agent_id": "rxcui:8782",
      "interaction_type": "unknown",
      "direction": "unclear",
      "source": "DGIdb",
      "source_url": "https://dgidb.org/genes/SCN2A",
      "evidence_tier": "mechanistic",
      "potency": {
        "value": null,
        "unit": null,
        "measure": null
      },
      "pubmed_ids": [],
      "raw": {
        "score": 0.05346011117141375
      }
    },
    {
      "agent": "OXCARBAZEPINE",
      "agent_id": "rxcui:32624",
      "interaction_type": "blocker",
      "direction": "inhibits",
      "source": "DGIdb",
      "source_url": "https://dgidb.org/genes/SCN2A",
      "evidence_tier": "mechanistic",
      "potency": {
        "value": null,
        "unit": null,
        "measure": null
      },
      "pubmed_ids": [],
      "raw": {
        "score": 0.04603509573093962
      }
    },
    {
      "agent": "SAFINAMIDE",
      "agent_id": "rxcui:1922448",
      "interaction_type": "unknown",
      "direction": "unclear",
      "source": "DGIdb",
      "source_url": "https://dgidb.org/genes/SCN2A",
      "evidence_tier": "mechanistic",
      "potency": {
        "value": null,
        "unit": null,
        "measure": null
      },
      "pubmed_ids": [],
      "raw": {
        "score": 0.05524211487712754
      }
    },
    {
      "agent": "PROCAINAMIDE HYDROCHLORIDE",
      "agent_id": "rxcui:155056",
      "interaction_type": "blocker",
      "direction": "inhibits",
      "source": "DGIdb",
      "source_url": "https://dgidb.org/genes/SCN2A",
      "evidence_tier": "mechanistic",
      "potency": {
        "value": null,
        "unit": null,
        "measure": null
      },
      "pubmed_ids": [],
      "raw": {
        "score": 0.0828631723156913
      }
    },
    {
      "agent": "PROPOXYCAINE HYDROCHLORIDE",
      "agent_id": "ncit:C66493",
      "interaction_type": "blocker",
      "direction": "inhibits",
      "source": "DGIdb",
      "source_url": "https://dgidb.org/genes/SCN2A",
      "evidence_tier": "mechanistic",
      "potency": {
        "value": null,
        "unit": null,
        "measure": null
      },
      "pubmed_ids": [],
      "raw": {
        "score": 0.0828631723156913
      }
    },
    {
      "agent": "MERETHOXYLLINE PROCAINE",
      "agent_id": "chembl:CHEMBL1200443",
      "interaction_type": "blocker",
      "direction": "inhibits",
      "source": "DGIdb",
      "source_url": "https://dgidb.org/genes/SCN2A",
      "evidence_tier": "mechanistic",
      "potency": {
        "value": null,
        "unit": null,
        "measure": null
      },
      "pubmed_ids": [],
      "raw": {
        "score": 0.0828631723156913
      }
    },
    {
      "agent": "DISOPYRAMIDE PHOSPHATE",
      "agent_id": "rxcui:203178",
      "interaction_type": "blocker",
      "direction": "inhibits",
      "source": "DGIdb",
      "source_url": "https://dgidb.org/genes/SCN2A",
      "evidence_tier": "mechanistic",
      "potency": {
        "value": null,
        "unit": null,
        "measure": null
      },
      "pubmed_ids": [],
      "raw": {
        "score": 0.07533015665062848
      }
    },
    {
      "agent": "TOCAINIDE HYDROCHLORIDE",
      "agent_id": "ncit:C47761",
      "interaction_type": "blocker",
      "direction": "inhibits",
      "source": "DGIdb",
      "source_url": "https://dgidb.org/genes/SCN2A",
      "evidence_tier": "mechanistic",
      "potency": {
        "value": null,
        "unit": null,
        "measure": null
      },
      "pubmed_ids": [],
      "raw": {
        "score": 0.0828631723156913
      }
    },
    {
      "agent": "TOPIRAMATE",
      "agent_id": "rxcui:38404",
      "interaction_type": "blocker",
      "direction": "inhibits",
      "source": "DGIdb",
      "source_url": "https://dgidb.org/genes/SCN2A",
      "evidence_tier": "mechanistic",
      "potency": {
        "value": null,
        "unit": null,
        "measure": null
      },
      "pubmed_ids": [
        "18784617"
      ],
      "raw": {
        "score": 0.05649761748797135
      }
    },
    {
      "agent": "PRILOCAINE",
      "agent_id": "rxcui:8686",
      "interaction_type": "blocker",
      "direction": "inhibits",
      "source": "DGIdb",
      "source_url": "https://dgidb.org/genes/SCN2A",
      "evidence_tier": "mechanistic",
      "potency": {
        "value": null,
        "unit": null,
        "measure": null
      },
      "pubmed_ids": [],
      "raw": {
        "score": 0.07533015665062848
      }
    },
    {
      "agent": "CENOBAMATE",
      "agent_id": "rxcui:2265690",
      "interaction_type": "inhibitor",
      "direction": "inhibits",
      "source": "DGIdb",
      "source_url": "https://dgidb.org/genes/SCN2A",
      "evidence_tier": "mechanistic",
      "potency": {
        "value": null,
        "unit": null,
        "measure": null
      },
      "pubmed_ids": [],
      "raw": {
        "score": 0.0295939901127469
      }
    },
    {
      "agent": "NKTR-171",
      "agent_id": "chembl:CHEMBL3545209",
      "interaction_type": "blocker",
      "direction": "inhibits",
      "source": "DGIdb",
      "source_url": "https://dgidb.org/genes/SCN2A",
      "evidence_tier": "mechanistic",
      "potency": {
        "value": null,
        "unit": null,
        "measure": null
      },
      "pubmed_ids": [],
      "raw": {
        "score": 0.0828631723156913
      }
    },
    {
      "agent": "PHENYTOIN SODIUM",
      "agent_id": "rxcui:71227",
      "interaction_type": "blocker",
      "direction": "inhibits",
      "source": "DGIdb",
      "source_url": "https://dgidb.org/genes/SCN2A",
      "evidence_tier": "mechanistic",
      "potency": {
        "value": null,
        "unit": null,
        "measure": null
      },
      "pubmed_ids": [
        "23859570",
        "18784617",
        "21747585",
        "19694741",
        "25155934"
      ],
      "raw": {
        "score": 0.1381052871928188
      }
    },
    {
      "agent": "QUINIDINE SULFATE",
      "agent_id": "rxcui:9069",
      "interaction_type": "blocker",
      "direction": "inhibits",
      "source": "DGIdb",
      "source_url": "https://dgidb.org/genes/SCN2A",
      "evidence_tier": "mechanistic",
      "potency": {
        "value": null,
        "unit": null,
        "measure": null
      },
      "pubmed_ids": [],
      "raw": {
        "score": 0.0828631723156913
      }
    },
    {
      "agent": "TETRACAINE",
      "agent_id": "rxcui:10391",
      "interaction_type": "blocker",
      "direction": "inhibits",
      "source": "DGIdb",
      "source_url": "https://dgidb.org/genes/SCN2A",
      "evidence_tier": "mechanistic",
      "potency": {
        "value": null,
        "unit": null,
        "measure": null
      },
      "pubmed_ids": [],
      "raw": {
        "score": 0.07533015665062848
      }
    },
    {
      "agent": "DRONEDARONE HYDROCHLORIDE",
      "agent_id": "rxcui:736680",
      "interaction_type": "blocker",
      "direction": "inhibits",
      "source": "DGIdb",
      "source_url": "https://dgidb.org/genes/SCN2A",
      "evidence_tier": "mechanistic",
      "potency": {
        "value": null,
        "unit": null,
        "measure": null
      },
      "pubmed_ids": [],
      "raw": {
        "score": 0.05178948269730707
      }
    },
    {
      "agent": "PHENAZOPYRIDINE HYDROCHLORIDE",
      "agent_id": "rxcui:203197",
      "interaction_type": "blocker",
      "direction": "inhibits",
      "source": "DGIdb",
      "source_url": "https://dgidb.org/genes/SCN2A",
      "evidence_tier": "mechanistic",
      "potency": {
        "value": null,
        "unit": null,
        "measure": null
      },
      "pubmed_ids": [],
      "raw": {
        "score": 0.05178948269730707
      }
    },
    {
      "agent": "FOSPROPOFOL",
      "agent_id": "rxcui:828682",
      "interaction_type": "unknown",
      "direction": "unclear",
      "source": "DGIdb",
      "source_url": "https://dgidb.org/genes/SCN2A",
      "evidence_tier": "mechanistic",
      "potency": {
        "value": null,
        "unit": null,
        "measure": null
      },
      "pubmed_ids": [],
      "raw": {
        "score": 0.2071579307892282
      }
    },
    {
      "agent": "RALFINAMIDE",
      "agent_id": "chembl:CHEMBL2107771",
      "interaction_type": "blocker",
      "direction": "inhibits",
      "source": "DGIdb",
      "source_url": "https://dgidb.org/genes/SCN2A",
      "evidence_tier": "mechanistic",
      "potency": {
        "value": null,
        "unit": null,
        "measure": null
      },
      "pubmed_ids": [],
      "raw": {
        "score": 0.04143158615784565
      }
    },
    {
      "agent": "ESLICARBAZEPINE ACETATE",
      "agent_id": "rxcui:1482501",
      "interaction_type": "blocker",
      "direction": "inhibits",
      "source": "DGIdb",
      "source_url": "https://dgidb.org/genes/SCN2A",
      "evidence_tier": "mechanistic",
      "potency": {
        "value": null,
        "unit": null,
        "measure": null
      },
      "pubmed_ids": [],
      "raw": {
        "score": 0.07533015665062848
      }
    },
    {
      "agent": "LIDOCAINE HYDROCHLORIDE",
      "agent_id": "rxcui:142440",
      "interaction_type": "blocker",
      "direction": "inhibits",
      "source": "DGIdb",
      "source_url": "https://dgidb.org/genes/SCN2A",
      "evidence_tier": "mechanistic",
      "potency": {
        "value": null,
        "unit": null,
        "measure": null
      },
      "pubmed_ids": [],
      "raw": {
        "score": 0.0828631723156913
      }
    },
    {
      "agent": "MEPIVACAINE HYDROCHLORIDE",
      "agent_id": "rxcui:203185",
      "interaction_type": "blocker",
      "direction": "inhibits",
      "source": "DGIdb",
      "source_url": "https://dgidb.org/genes/SCN2A",
      "evidence_tier": "mechanistic",
      "potency": {
        "value": null,
        "unit": null,
        "measure": null
      },
      "pubmed_ids": [],
      "raw": {
        "score": 0.05178948269730707
      }
    },
    {
      "agent": "ORPHENADRINE HYDROCHLORIDE",
      "agent_id": "rxcui:202723",
      "interaction_type": "blocker",
      "direction": "inhibits",
      "source": "DGIdb",
      "source_url": "https://dgidb.org/genes/SCN2A",
      "evidence_tier": "mechanistic",
      "potency": {
        "value": null,
        "unit": null,
        "measure": null
      },
      "pubmed_ids": [],
      "raw": {
        "score": 0.04361219595562701
      }
    },
    {
      "agent": "LAMOTRIGINE",
      "agent_id": "rxcui:28439",
      "interaction_type": "blocker",
      "direction": "inhibits",
      "source": "DGIdb",
      "source_url": "https://dgidb.org/genes/SCN2A",
      "evidence_tier": "mechanistic",
      "potency": {
        "value": null,
        "unit": null,
        "measure": null
      },
      "pubmed_ids": [
        "18784617"
      ],
      "raw": {
        "score": 0.1506603133012569
      }
    },
    {
      "agent": "DYCLONINE HYDROCHLORIDE",
      "agent_id": "rxcui:91188",
      "interaction_type": "blocker",
      "direction": "inhibits",
      "source": "DGIdb",
      "source_url": "https://dgidb.org/genes/SCN2A",
      "evidence_tier": "mechanistic",
      "potency": {
        "value": null,
        "unit": null,
        "measure": null
      },
      "pubmed_ids": [],
      "raw": {
        "score": 0.05178948269730707
      }
    },
    {
      "agent": "TETRODOTOXIN",
      "agent_id": "ncit:C78845",
      "interaction_type": "unknown",
      "direction": "unclear",
      "source": "DGIdb",
      "source_url": "https://dgidb.org/genes/SCN2A",
      "evidence_tier": "mechanistic",
      "potency": {
        "value": null,
        "unit": null,
        "measure": null
      },
      "pubmed_ids": [],
      "raw": {
        "score": 0.0828631723156913
      }
    },
    {
      "agent": "MEXILETINE HYDROCHLORIDE",
      "agent_id": "rxcui:142138",
      "interaction_type": "blocker",
      "direction": "inhibits",
      "source": "DGIdb",
      "source_url": "https://dgidb.org/genes/SCN2A",
      "evidence_tier": "mechanistic",
      "potency": {
        "value": null,
        "unit": null,
        "measure": null
      },
      "pubmed_ids": [],
      "raw": {
        "score": 0.0828631723156913
      }
    },
    {
      "agent": "ZONISAMIDE",
      "agent_id": "rxcui:39998",
      "interaction_type": "blocker",
      "direction": "inhibits",
      "source": "DGIdb",
      "source_url": "https://dgidb.org/genes/SCN2A",
      "evidence_tier": "mechanistic",
      "potency": {
        "value": null,
        "unit": null,
        "measure": null
      },
      "pubmed_ids": [],
      "raw": {
        "score": 0.06629053785255305
      }
    },
    {
      "agent": "PHENOBARBITAL",
      "agent_id": "rxcui:8134",
      "interaction_type": "unknown",
      "direction": "unclear",
      "source": "DGIdb",
      "source_url": "https://dgidb.org/genes/SCN2A",
      "evidence_tier": "mechanistic",
      "potency": {
        "value": null,
        "unit": null,
        "measure": null
      },
      "pubmed_ids": [
        "23859570",
        "21747585",
        "19694741",
        "25155934"
      ],
      "raw": {
        "score": 0.1090304898890675
      }
    },
    {
      "agent": "LACOSAMIDE",
      "agent_id": "rxcui:623400",
      "interaction_type": "blocker",
      "direction": "inhibits",
      "source": "DGIdb",
      "source_url": "https://dgidb.org/genes/SCN2A",
      "evidence_tier": "mechanistic",
      "potency": {
        "value": null,
        "unit": null,
        "measure": null
      },
      "pubmed_ids": [],
      "raw": {
        "score": 0.06374090178130101
      }
    },
    {
      "agent": "IRAMPANEL",
      "agent_id": "ncit:C65960",
      "interaction_type": "blocker",
      "direction": "inhibits",
      "source": "DGIdb",
      "source_url": "https://dgidb.org/genes/SCN2A",
      "evidence_tier": "mechanistic",
      "potency": {
        "value": null,
        "unit": null,
        "measure": null
      },
      "pubmed_ids": [],
      "raw": {
        "score": 0.0591879802254938
      }
    },
    {
      "agent": "FOSPHENYTOIN",
      "agent_id": "rxcui:72236",
      "interaction_type": "blocker",
      "direction": "inhibits",
      "source": "DGIdb",
      "source_url": "https://dgidb.org/genes/SCN2A",
      "evidence_tier": "mechanistic",
      "potency": {
        "value": null,
        "unit": null,
        "measure": null
      },
      "pubmed_ids": [],
      "raw": {
        "score": 0.06374090178130101
      }
    },
    {
      "agent": "MORICIZINE HYDROCHLORIDE",
      "agent_id": "rxcui:221126",
      "interaction_type": "blocker",
      "direction": "inhibits",
      "source": "DGIdb",
      "source_url": "https://dgidb.org/genes/SCN2A",
      "evidence_tier": "mechanistic",
      "potency": {
        "value": null,
        "unit": null,
        "measure": null
      },
      "pubmed_ids": [],
      "raw": {
        "score": 0.06905264359640943
      }
    },
    {
      "agent": "RILUZOLE",
      "agent_id": "rxcui:35623",
      "interaction_type": "blocker",
      "direction": "inhibits",
      "source": "DGIdb",
      "source_url": "https://dgidb.org/genes/SCN2A",
      "evidence_tier": "mechanistic",
      "potency": {
        "value": null,
        "unit": null,
        "measure": null
      },
      "pubmed_ids": [],
      "raw": {
        "score": 0.03602746622421362
      }
    },
    {
      "agent": "PHENACEMIDE",
      "agent_id": "rxcui:33253",
      "interaction_type": "blocker",
      "direction": "inhibits",
      "source": "DGIdb",
      "source_url": "https://dgidb.org/genes/SCN2A",
      "evidence_tier": "mechanistic",
      "potency": {
        "value": null,
        "unit": null,
        "measure": null
      },
      "pubmed_ids": [],
      "raw": {
        "score": 0.07533015665062848
      }
    },
    {
      "agent": "PROPAFENONE HYDROCHLORIDE",
      "agent_id": "rxcui:203135",
      "interaction_type": "blocker",
      "direction": "inhibits",
      "source": "DGIdb",
      "source_url": "https://dgidb.org/genes/SCN2A",
      "evidence_tier": "mechanistic",
      "potency": {
        "value": null,
        "unit": null,
        "measure": null
      },
      "pubmed_ids": [],
      "raw": {
        "score": 0.0591879802254938
      }
    },
    {
      "agent": "ORPHENADRINE CITRATE",
      "agent_id": "rxcui:7716",
      "interaction_type": "blocker",
      "direction": "inhibits",
      "source": "DGIdb",
      "source_url": "https://dgidb.org/genes/SCN2A",
      "evidence_tier": "mechanistic",
      "potency": {
        "value": null,
        "unit": null,
        "measure": null
      },
      "pubmed_ids": [],
      "raw": {
        "score": 0.03945865348366253
      }
    },
    {
      "agent": "PRIMIDONE",
      "agent_id": "rxcui:8691",
      "interaction_type": "blocker",
      "direction": "inhibits",
      "source": "DGIdb",
      "source_url": "https://dgidb.org/genes/SCN2A",
      "evidence_tier": "mechanistic",
      "potency": {
        "value": null,
        "unit": null,
        "measure": null
      },
      "pubmed_ids": [],
      "raw": {
        "score": 0.02367519209019752
      }
    },
    {
      "agent": "ENCAINIDE HYDROCHLORIDE",
      "agent_id": "rxcui:281189",
      "interaction_type": "blocker",
      "direction": "inhibits",
      "source": "DGIdb",
      "source_url": "https://dgidb.org/genes/SCN2A",
      "evidence_tier": "mechanistic",
      "potency": {
        "value": null,
        "unit": null,
        "measure": null
      },
      "pubmed_ids": [],
      "raw": {
        "score": 0.0828631723156913
      }
    },
    {
      "agent": "ARTICAINE HYDROCHLORIDE",
      "agent_id": "rxcui:2117",
      "interaction_type": "blocker",
      "direction": "inhibits",
      "source": "DGIdb",
      "source_url": "https://dgidb.org/genes/SCN2A",
      "evidence_tier": "mechanistic",
      "potency": {
        "value": null,
        "unit": null,
        "measure": null
      },
      "pubmed_ids": [],
      "raw": {
        "score": 0.0828631723156913
      }
    },
    {
      "agent": "ELPETRIGINE",
      "agent_id": "ncit:C166519",
      "interaction_type": "blocker",
      "direction": "inhibits",
      "source": "DGIdb",
      "source_url": "https://dgidb.org/genes/SCN2A",
      "evidence_tier": "mechanistic",
      "potency": {
        "value": null,
        "unit": null,
        "measure": null
      },
      "pubmed_ids": [],
      "raw": {
        "score": 0.09207019146187924
      }
    },
    {
      "agent": "HEXYLCAINE HYDROCHLORIDE",
      "agent_id": "rxcui:1546032",
      "interaction_type": "blocker",
      "direction": "inhibits",
      "source": "DGIdb",
      "source_url": "https://dgidb.org/genes/SCN2A",
      "evidence_tier": "mechanistic",
      "potency": {
        "value": null,
        "unit": null,
        "measure": null
      },
      "pubmed_ids": [],
      "raw": {
        "score": 0.0828631723156913
      }
    },
    {
      "agent": "ANTICONVULSANT AGENT",
      "agent_id": "ncit:C264",
      "interaction_type": "unknown",
      "direction": "unclear",
      "source": "DGIdb",
      "source_url": "https://dgidb.org/genes/SCN2A",
      "evidence_tier": "mechanistic",
      "potency": {
        "value": null,
        "unit": null,
        "measure": null
      },
      "pubmed_ids": [
        "23859570",
        "18784617",
        "21747585",
        "19694741",
        "25155934"
      ],
      "raw": {
        "score": 0.3314526892627653
      }
    },
    {
      "agent": "MEPHENYTOIN",
      "agent_id": "rxcui:6757",
      "interaction_type": "blocker",
      "direction": "inhibits",
      "source": "DGIdb",
      "source_url": "https://dgidb.org/genes/SCN2A",
      "evidence_tier": "mechanistic",
      "potency": {
        "value": null,
        "unit": null,
        "measure": null
      },
      "pubmed_ids": [],
      "raw": {
        "score": 0.06905264359640943
      }
    },
    {
      "agent": "EVENAMIDE",
      "agent_id": "ncit:C174804",
      "interaction_type": "blocker",
      "direction": "inhibits",
      "source": "DGIdb",
      "source_url": "https://dgidb.org/genes/SCN2A",
      "evidence_tier": "mechanistic",
      "potency": {
        "value": null,
        "unit": null,
        "measure": null
      },
      "pubmed_ids": [],
      "raw": {
        "score": 0.0828631723156913
      }
    },
    {
      "agent": "LIDOCAINE",
      "agent_id": "rxcui:6387",
      "interaction_type": "blocker",
      "direction": "inhibits",
      "source": "DGIdb",
      "source_url": "https://dgidb.org/genes/SCN2A",
      "evidence_tier": "mechanistic",
      "potency": {
        "value": null,
        "unit": null,
        "measure": null
      },
      "pubmed_ids": [],
      "raw": {
        "score": 0.04874304253864195
      }
    },
    {
      "agent": "INDECAINIDE HYDROCHLORIDE",
      "agent_id": "ncit:C65911",
      "interaction_type": "blocker",
      "direction": "inhibits",
      "source": "DGIdb",
      "source_url": "https://dgidb.org/genes/SCN2A",
      "evidence_tier": "mechanistic",
      "potency": {
        "value": null,
        "unit": null,
        "measure": null
      },
      "pubmed_ids": [],
      "raw": {
        "score": 0.0828631723156913
      }
    },
    {
      "agent": "COCAINE HYDROCHLORIDE",
      "agent_id": "rxcui:81985",
      "interaction_type": "blocker",
      "direction": "inhibits",
      "source": "DGIdb",
      "source_url": "https://dgidb.org/genes/SCN2A",
      "evidence_tier": "mechanistic",
      "potency": {
        "value": null,
        "unit": null,
        "measure": null
      },
      "pubmed_ids": [],
      "raw": {
        "score": 0.0828631723156913
      }
    },
    {
      "agent": "ETIDOCAINE HYDROCHLORIDE",
      "agent_id": "rxcui:227221",
      "interaction_type": "blocker",
      "direction": "inhibits",
      "source": "DGIdb",
      "source_url": "https://dgidb.org/genes/SCN2A",
      "evidence_tier": "mechanistic",
      "potency": {
        "value": null,
        "unit": null,
        "measure": null
      },
      "pubmed_ids": [],
      "raw": {
        "score": 0.0828631723156913
      }
    },
    {
      "agent": "DICHLOROBENZYL ALCOHOL",
      "agent_id": "rxcui:22906",
      "interaction_type": "blocker",
      "direction": "inhibits",
      "source": "DGIdb",
      "source_url": "https://dgidb.org/genes/SCN2A",
      "evidence_tier": "mechanistic",
      "potency": {
        "value": null,
        "unit": null,
        "measure": null
      },
      "pubmed_ids": [],
      "raw": {
        "score": 0.0828631723156913
      }
    },
    {
      "agent": "RUFINAMIDE",
      "agent_id": "rxcui:69036",
      "interaction_type": "blocker",
      "direction": "inhibits",
      "source": "DGIdb",
      "source_url": "https://dgidb.org/genes/SCN2A",
      "evidence_tier": "mechanistic",
      "potency": {
        "value": null,
        "unit": null,
        "measure": null
      },
      "pubmed_ids": [],
      "raw": {
        "score": 0.06905264359640943
      }
    },
    {
      "agent": "NERISPIRDINE",
      "agent_id": "ncit:C80997",
      "interaction_type": "blocker",
      "direction": "inhibits",
      "source": "DGIdb",
      "source_url": "https://dgidb.org/genes/SCN2A",
      "evidence_tier": "mechanistic",
      "potency": {
        "value": null,
        "unit": null,
        "measure": null
      },
      "pubmed_ids": [],
      "raw": {
        "score": 0.01657263446313826
      }
    },
    {
      "agent": "PROPARACAINE HYDROCHLORIDE",
      "agent_id": "rxcui:227778",
      "interaction_type": "blocker",
      "direction": "inhibits",
      "source": "DGIdb",
      "source_url": "https://dgidb.org/genes/SCN2A",
      "evidence_tier": "mechanistic",
      "potency": {
        "value": null,
        "unit": null,
        "measure": null
      },
      "pubmed_ids": [],
      "raw": {
        "score": 0.0828631723156913
      }
    },
    {
      "agent": "ESLICARBAZEPINE",
      "agent_id": "rxcui:1482502",
      "interaction_type": "blocker",
      "direction": "inhibits",
      "source": "DGIdb",
      "source_url": "https://dgidb.org/genes/SCN2A",
      "evidence_tier": "mechanistic",
      "potency": {
        "value": null,
        "unit": null,
        "measure": null
      },
      "pubmed_ids": [],
      "raw": {
        "score": 0.07533015665062848
      }
    },
    {
      "agent": "CHLOROPROCAINE",
      "agent_id": "rxcui:20859",
      "interaction_type": "blocker",
      "direction": "inhibits",
      "source": "DGIdb",
      "source_url": "https://dgidb.org/genes/SCN2A",
      "evidence_tier": "mechanistic",
      "potency": {
        "value": null,
        "unit": null,
        "measure": null
      },
      "pubmed_ids": [],
      "raw": {
        "score": 0.06374090178130101
      }
    },
    {
      "agent": "CARBAMAZEPINE",
      "agent_id": "rxcui:2002",
      "interaction_type": "blocker",
      "direction": "inhibits",
      "source": "DGIdb",
      "source_url": "https://dgidb.org/genes/SCN2A",
      "evidence_tier": "mechanistic",
      "potency": {
        "value": null,
        "unit": null,
        "measure": null
      },
      "pubmed_ids": [],
      "raw": {
        "score": 0.01691085149299822
      }
    },
    {
      "agent": "QUINIDINE POLYGALACTURONATE",
      "agent_id": "rxcui:41875",
      "interaction_type": "blocker",
      "direction": "inhibits",
      "source": "DGIdb",
      "source_url": "https://dgidb.org/genes/SCN2A",
      "evidence_tier": "mechanistic",
      "potency": {
        "value": null,
        "unit": null,
        "measure": null
      },
      "pubmed_ids": [],
      "raw": {
        "score": 0.0828631723156913
      }
    },
    {
      "agent": "PRILOCAINE HYDROCHLORIDE",
      "agent_id": "rxcui:2557",
      "interaction_type": "blocker",
      "direction": "inhibits",
      "source": "DGIdb",
      "source_url": "https://dgidb.org/genes/SCN2A",
      "evidence_tier": "mechanistic",
      "potency": {
        "value": null,
        "unit": null,
        "measure": null
      },
      "pubmed_ids": [],
      "raw": {
        "score": 0.07533015665062848
      }
    },
    {
      "agent": "ROPIVACAINE HYDROCHLORIDE",
      "agent_id": "rxcui:236539",
      "interaction_type": "blocker",
      "direction": "inhibits",
      "source": "DGIdb",
      "source_url": "https://dgidb.org/genes/SCN2A",
      "evidence_tier": "mechanistic",
      "potency": {
        "value": null,
        "unit": null,
        "measure": null
      },
      "pubmed_ids": [],
      "raw": {
        "score": 0.0828631723156913
      }
    },
    {
      "agent": "ETHOTOIN",
      "agent_id": "rxcui:4136",
      "interaction_type": "blocker",
      "direction": "inhibits",
      "source": "DGIdb",
      "source_url": "https://dgidb.org/genes/SCN2A",
      "evidence_tier": "mechanistic",
      "potency": {
        "value": null,
        "unit": null,
        "measure": null
      },
      "pubmed_ids": [],
      "raw": {
        "score": 0.0828631723156913
      }
    },
    {
      "agent": "QUINIDINE GLUCONATE",
      "agent_id": "rxcui:35220",
      "interaction_type": "blocker",
      "direction": "inhibits",
      "source": "DGIdb",
      "source_url": "https://dgidb.org/genes/SCN2A",
      "evidence_tier": "mechanistic",
      "potency": {
        "value": null,
        "unit": null,
        "measure": null
      },
      "pubmed_ids": [],
      "raw": {
        "score": 0.0828631723156913
      }
    },
    {
      "agent": "BENOXINATE HYDROCHLORIDE",
      "agent_id": "rxcui:235398",
      "interaction_type": "blocker",
      "direction": "inhibits",
      "source": "DGIdb",
      "source_url": "https://dgidb.org/genes/SCN2A",
      "evidence_tier": "mechanistic",
      "potency": {
        "value": null,
        "unit": null,
        "measure": null
      },
      "pubmed_ids": [],
      "raw": {
        "score": 0.07533015665062848
      }
    }
  ]
}